jupyter_dark_detect/__init__.py
jupyter_dark_detect/detector.py
jupyter_dark_detect-0.1.0.dist-info/licenses/LICENSE
tests/__init__.py
tests/test_detector.py
jupyter_dark_detect-0.1.0.dist-info/METADATA
jupyter_dark_detect-0.1.0.dist-info/WHEEL
jupyter_dark_detect-0.1.0.dist-info/top_level.txt
jupyter_dark_detect-0.1.0.dist-info/RECORD
