Metadata-Version: 2.4
Name: jupyter-dark-detect
Version: 0.1.0
Summary: Detect dark mode in Jupyter environments
Home-page: https://github.com/yourusername/jupyter-dark-detect
Author: Your Name
Author-email: your.email@example.com
License: MIT
Keywords: jupyter notebook jupyterlab dark-mode theme detection
Classifier: Development Status :: 4 - Beta
Classifier: Intended Audience :: Developers
Classifier: Topic :: Software Development :: Libraries :: Python Modules
Classifier: Programming Language :: Python :: 3
Classifier: Programming Language :: Python :: 3.7
Classifier: Programming Language :: Python :: 3.8
Classifier: Programming Language :: Python :: 3.9
Classifier: Programming Language :: Python :: 3.10
Classifier: Programming Language :: Python :: 3.11
Classifier: Programming Language :: Python :: 3.12
Classifier: Framework :: Jupyter
Classifier: Framework :: Jupyter :: JupyterLab
Classifier: Environment :: Web Environment
Requires-Python: >=3.7
License-File: LICENSE
Requires-Dist: ipython>=7.0.0
Dynamic: author
Dynamic: author-email
Dynamic: classifier
Dynamic: description
Dynamic: description-content-type
Dynamic: home-page
Dynamic: keywords
Dynamic: license
Dynamic: license-file
Dynamic: requires-dist
Dynamic: requires-python
Dynamic: summary
